{
    "scopes": [
        {
            "name": "accounts_info.write",
            "test_endpoint": "/2/account/set_profile_photo"
        },
        {
            "name": "files.metadata.write",
            "test_endpoint": "/2/file_properties/properties/add",
            "implied_scopes": [
                "files.metadata.read"
            ]
        },
        {
            "name": "files.metadata.read",
            "test_endpoint": "/2/file_properties/properties/search"
        },
        {
            "name": "files.content.write",
            "test_endpoint": "/2/files/copy_v2",
            "implied_scopes": [
                "files.metadata.read"
            ]
        },
        {
            "name": "files.content.read",
            "test_endpoint": "/2/files/get_file_lock_batch"
        },
        {
            "name": "sharing.write",
            "test_endpoint": "/2/sharing/add_file_member",
            "implied_scopes": [
                "sharing.read"
            ]
        },
        {
            "name": "sharing.read",
            "test_endpoint": "/2/sharing/get_file_metadata"
        },
        {
            "name": "file_requests.write",
            "test_endpoint": "/2/file_requests/update",
            "implied_scopes": [
                "file_requests.read"
            ]
        },
        {
            "name": "file_requests.read",
            "test_endpoint": "/2/file_requests/list/continue"
        },
        {
            "name": "contacts.write",
            "test_endpoint": "/2/contacts/delete_manual_contacts_batch",
            "implied_scopes": [
                "contacts.read"
            ]
        },
        {
            "name": "openid",
            "test_endpoint": "/2/openid/userinfo"
        }
    ]
}